sesparser/__init__.py
sesparser/__version__.py
sesparser/attachments.py
sesparser/body.py
sesparser/headers.py
sesparser/main.py
sesparser/parse_it.py
sesparser/store_aws.py
sesparser-1.9.4.5.dist-info/METADATA
sesparser-1.9.4.5.dist-info/WHEEL
sesparser-1.9.4.5.dist-info/licenses/LICENSE
sesparser-1.9.4.5.dist-info/licenses/NOTICE
sesparser-1.9.4.5.dist-info/RECORD
