Metadata-Version: 2.1
Name: sesparser
Version: 1.9.4.5
Summary: AWS SES Email Parser
Project-URL: Homepage, https://github.com/suryavaddiraju/sesparser
Project-URL: Bug Tracker, https://github.com/suryavaddiraju/sesparser/issues
Project-URL: Documentation, https://sesparser.readthedocs.io
Author-email: Vaddiraju Surya Teja <suryavaddiraju@proton.me>
License-Expression: Apache-2.0
License-File: LICENSE
License-File: NOTICE
Keywords: AWS,SES,attachments,aws ses,body,dynamodb,email,email body,email parser,inline,inline attachments,lambda,lambda layer,layer,parser,ses parser
Classifier: License :: OSI Approved :: Apache Software License
Classifier: Operating System :: OS Independent
Classifier: Programming Language :: Python :: 3
Requires-Python: >=3.8
Requires-Dist: boto3>=1.28.74
Requires-Dist: chardet>=5.2.0
Requires-Dist: pytz>=2023.3
